clabeler/__init__.py
clabeler/command_line.py
clabeler-1.0.2.dist-info/LICENSE
clabeler-1.0.2.dist-info/METADATA
clabeler-1.0.2.dist-info/WHEEL
clabeler-1.0.2.dist-info/entry_points.txt
clabeler-1.0.2.dist-info/top_level.txt
clabeler-1.0.2.dist-info/RECORD
