Metadata-Version: 2.1
Name: clabeler
Version: 1.0.2
Summary: Label exam PDFs from Crowdmark with names of students
Home-page: https://github.com/mwt/crowdmark-labeler
Author: Matthew Thomas
Author-email: matthew.thomas@northwestern.edu
License: MIT License
Project-URL: Bug Tracker, https://github.com/mwt/crowdmark-labeler/issues
Platform: OS Independent
Classifier: Programming Language :: Python :: 3
Classifier: License :: OSI Approved :: MIT License
Classifier: Operating System :: OS Independent
Requires-Python: >=3.4
Requires-Dist: pandas
Requires-Dist: pdfrw
Requires-Dist: reportlab
